{
    "endCondition": {
        "None_None": 0.07692307692307694,
        "None_adjAll": 0.986013986013986,
        "None_advMode": 0.7482517482517482,
        "None_advTime": 0.5594405594405595,
        "None_sustAbstract": 0.7832167832167831,
        "None_sustAll": 0.5804195804195804,
        "adjAll_sustAll": 0.15384615384615385,
        "adjQualifying_None": 0.37762237762237727,
        "adjQualifying_sustAbstract": 0.3986013986013989,
        "adjUndefined_None": 0.4825174825174825,
        "advComparative_advPlace": 0.2097902097902099,
        "advComparative_advTime": 0.04895104895104897,
        "advPlace_punctuation": 0.11888111888111888,
        "advQuantity_advMode": 0.6783216783216783,
        "advTime_advTime": 0.1608391608391609,
        "conjComparative_ipi": 0.9300699300699301,
        "conjComparative_pronPersonal": 0.9020979020979021,
        "detArticle_None": 0.14685314685314685,
        "detArticle_adjAll": 0.3146853146853147,
        "detArticle_ipps": 0.9370629370629371,
        "detArticle_sustAbstract": 0.14685314685314688,
        "detArticle_sustAll": 0.11888111888111895,
        "detArticle_sustPropio": 0.055944055944055944,
        "detPossesive_None": 0.6923076923076923,
        "detPossesive_sustDisminutivo": 0.27272727272727265,
        "detPossesive_sustPropio": 0.4265734265734269,
        "detPossesive_sustSimple": 0.3566433566433567,
        "detUndefined_None": 0.27272727272727265,
        "detUndefined_adjAll": 0.6573426573426573,
        "detUndefined_adjQualifying": 0.5524475524475524,
        "detUndefined_sustAll": 0.34965034965034963,
        "detUndefined_sustCompuesto": 0.5734265734265734,
        "detUndefined_sustDisminutivo": 0.6013986013986014,
        "detUndefined_sustPropio": 0.2867132867132867,
        "detUndefined_sustSimple": 0.44755244755244755,
        "i_None": 0.8811188811188809,
        "i_adjAll": 0.4965034965034965,
        "i_inf": 0.44755244755244755,
        "if_adjAll": 0.6503496503496503,
        "if_adjQualifying": 0.29370629370629375,
        "if_adjSuperlative": 0.07692307692307693,
        "inf_advMode": 0.5174825174825175,
        "inf_pronAll": 0.5244755244755245,
        "ip_None": 0.32867132867132876,
        "ip_adjAll": 0.4755244755244755,
        "ip_sustAll": 0.09090909090909091,
        "ipi_adjAll": 0.7692307692307693,
        "ipi_sustAll": 0.6433566433566434,
        "ipi_sustDisminutivo": 0.6293706293706294,
        "ipps_pronPersonal": 0.1958041958041959,
        "ipps_sustCompuesto": 0.3076923076923077,
        "number_None": 0.08391608391608392,
        "prepPosesion_None": 0.06993006993006994,
        "prepPosesion_adjAll": 0.8671328671328671,
        "prepPosesion_adjQualifying": 0.26573426573426573,
        "prepPosesion_advTime": 0.5384615384615385,
        "prepPosesion_sustAll": 0.5804195804195804,
        "prepPosesion_sustSimple": 0.4055944055944057,
        "prepProper_None": 0.4965034965034965,
        "prepProper_advTime": 0.20279720279720284,
        "prepProper_ip": 0.46153846153846156,
        "prepProper_sustAll": 0.5594405594405595,
        "prepTemporal_None": 0.6223776223776225,
        "prepTemporal_inf": 0.006993006993006993,
        "prepUbication_None": 0.7062937062937064,
        "prepUbication_sustSimple": 0.02097902097902096,
        "pronAll_None": 0.04895104895104894,
        "pronAll_sustAbstract": 0.9230769230769231,
        "pronUndefined_sustAll": 0.5944055944055945,
        "sp_i": 0.41258741258741255,
        "sustAbstract_None": 0.23076923076923078,
        "sustAbstract_punctuation": 0.18881118881118888,
        "sustAll_None": 0.8531468531468531,
        "sustAll_adjQualifying": 0.3426573426573425,
        "sustAll_punctuation": 0.21678321678321677,
        "sustDespectivo_None": 0.09790209790209795,
        "sustDisminutivo_adjAll": 1.0,
        "sustPropio_adjAll": 0.3356643356643356,
        "sustSimple_None": 0.38461538461538464
    },
    "factCondition": 143.0,
    "factNounVrb": 119.0,
    "factPosVerb": 142.0,
    "factPreVerb": 139.0,
    "factPronVrb": 152.0,
    "factVerb": 148.0,
    "nounVerb": [
        [
            0.0,
            0.0,
            0.0,
            0.0,
            0.0,
            0.0,
            0.0,
            0.0,
            0.0,
            0.0
        ],
        [
            0.0,
            0.0,
            0.0,
            0.0,
            0.0,
            0.0,
            0.0,
            0.0,
            0.0,
            0.0
        ],
        [
            0.0,
            0.0,
            0.0,
            0.0,
            0.0,
            0.0,
            0.0,
            0.0,
            0.0,
            0.01680672268907563
        ],
        [
            0.04201680672268908,
            0.03361344537815126,
            0.0,
            0.01680672268907563,
            0.0,
            0.0,
            0.008403361344537815,
            0.0,
            0.025210084033613443,
            0.20168067226890757
        ],
        [
            0.008403361344537815,
            0.0,
            0.0,
            0.0,
            0.008403361344537815,
            0.0,
            0.0,
            0.0,
            0.008403361344537815,
            0.06722689075630252
        ],
        [
            0.0,
            0.0,
            0.0,
            0.0,
            0.0,
            0.0,
            0.008403361344537815,
            0.0,
            0.008403361344537815,
            0.05042016806722689
        ],
        [
            0.0,
            0.0,
            0.0,
            0.0,
            0.0,
            0.0,
            0.0,
            0.0,
            0.0,
            0.0
        ],
        [
            0.025210084033613446,
            0.050420168067226885,
            0.0,
            0.008403361344537815,
            0.0,
            0.0,
            0.008403361344537815,
            0.0,
            0.03361344537815126,
            0.18487394957983194
        ],
        [
            0.0,
            0.008403361344537815,
            0.0,
            0.0,
            0.0,
            0.0,
            0.01680672268907563,
            0.0,
            0.01680672268907563,
            0.12605042016806725
        ],
        [
            0.0,
            0.0,
            0.0,
            0.0,
            0.0,
            0.0,
            0.0,
            0.0,
            0.0,
            0.0
        ],
        [
            0.0,
            0.0,
            0.0,
            0.0,
            0.0,
            0.0,
            0.0,
            0.0,
            0.008403361344537815,
            0.008403361344537815
        ],
        [
            0.0,
            0.0,
            0.0,
            0.0,
            0.0,
            0.0,
            0.0,
            0.0,
            0.0,
            0.0
        ],
        [
            0.0,
            0.0,
            0.0,
            0.0,
            0.0,
            0.0,
            0.0,
            0.0,
            0.0,
            0.0
        ]
    ],
    "nucleous": [
        [
            0.0,
            0.0,
            0.0,
            0.0,
            0.0,
            0.0,
            0.0,
            0.0,
            0.0,
            0.0,
            0.0,
            0.0
        ],
        [
            0.0,
            0.0,
            0.020270270270270268,
            0.0,
            0.6081081081081081,
            0.0,
            0.013513513513513514,
            0.0,
            0.0,
            0.0,
            0.0,
            0.006756756756756757
        ],
        [
            0.027027027027027008,
            0.0,
            0.0,
            0.0,
            0.02702702702702703,
            0.0,
            0.0,
            0.0,
            0.0,
            0.0,
            0.0,
            0.0
        ],
        [
            0.0,
            0.0,
            0.0,
            0.0,
            0.0,
            0.0,
            0.0,
            0.0,
            0.0,
            0.0,
            0.0,
            0.0
        ],
        [
            0.2972972972972973,
            0.13513513513513517,
            0.0945945945945946,
            0.23648648648648643,
            0.040540540540540536,
            0.040540540540540536,
            0.027027027027027025,
            0.0,
            0.020270270270270264,
            0.020270270270270268,
            0.0,
            0.0
        ],
        [
            0.0,
            0.0,
            0.0,
            0.0,
            0.03378378378378378,
            0.0,
            0.0,
            0.0,
            0.0,
            0.0,
            0.0,
            0.0
        ],
        [
            0.0,
            0.020270270270270268,
            0.013513513513513514,
            0.0,
            0.06756756756756759,
            0.0,
            0.0,
            0.0,
            0.0,
            0.0,
            0.0,
            0.006756756756756757
        ],
        [
            0.0,
            0.0,
            0.0,
            0.0,
            0.0,
            0.0,
            0.0,
            0.0,
            0.0,
            0.0,
            0.0,
            0.0
        ],
        [
            0.0,
            0.0,
            0.0,
            0.0,
            0.006756756756756757,
            0.0,
            0.0,
            0.0,
            0.0,
            0.0,
            0.0,
            0.0
        ],
        [
            0.0,
            0.0,
            0.0,
            0.0,
            0.0,
            0.0,
            0.0,
            0.0,
            0.0,
            0.0,
            0.0,
            0.0
        ],
        [
            0.0,
            0.0,
            0.0,
            0.0,
            0.006756756756756757,
            0.0,
            0.0,
            0.0,
            0.0,
            0.0,
            0.0,
            0.0
        ],
        [
            0.0,
            0.0,
            0.0,
            0.0,
            0.1283783783783784,
            0.0,
            0.0,
            0.0,
            0.0,
            0.0,
            0.0,
            0.0
        ]
    ],
    "postVerb": [
        [
            0.0,
            0.0,
            0.0,
            0.09154929577464789,
            0.04929577464788732,
            0.02112676056338028,
            0.0,
            0.12676056338028174,
            0.04225352112676056,
            0.0,
            0.007042253521126761,
            0.0
        ],
        [
            0.0,
            0.0,
            0.0,
            0.07746478873239439,
            0.04225352112676056,
            0.014084507042253521,
            0.0,
            0.007042253521126761,
            0.014084507042253521,
            0.0,
            0.0,
            0.0
        ],
        [
            0.0,
            0.0,
            0.0,
            0.02112676056338028,
            0.014084507042253521,
            0.028169014084507043,
            0.0,
            0.014084507042253521,
            0.021126760563380278,
            0.0,
            0.0,
            0.0
        ],
        [
            0.0,
            0.0,
            0.007042253521126761,
            0.021126760563380264,
            0.07042253521126761,
            0.007042253521126761,
            0.0,
            0.09859154929577464,
            0.028169014084507043,
            0.0,
            0.014084507042253521,
            0.0
        ],
        [
            0.0,
            0.0,
            0.0,
            0.007042253521126761,
            0.0,
            0.007042253521126761,
            0.0,
            0.014084507042253521,
            0.014084507042253521,
            0.0,
            0.007042253521126761,
            0.0
        ],
        [
            0.0,
            0.0,
            0.0,
            0.007042253521126761,
            0.0,
            0.0,
            0.0,
            0.014084507042253521,
            0.014084507042253521,
            0.0,
            0.007042253521126761,
            0.0
        ],
        [
            0.0,
            0.0,
            0.0,
            0.0,
            0.007042253521126761,
            0.007042253521126761,
            0.0,
            0.014084507042253521,
            0.0,
            0.0,
            0.0,
            0.0
        ],
        [
            0.0,
            0.0,
            0.0,
            0.0,
            0.0,
            0.0,
            0.0,
            0.0,
            0.0,
            0.0,
            0.0,
            0.0
        ],
        [
            0.0,
            0.0,
            0.0,
            0.007042253521126761,
            0.0,
            0.0,
            0.0,
            0.014084507042253521,
            0.0,
            0.0,
            0.0,
            0.0
        ],
        [
            0.0,
            0.0,
            0.0,
            0.014084507042253521,
            0.0,
            0.0,
            0.0,
            0.0,
            0.007042253521126761,
            0.0,
            0.0,
            0.0
        ],
        [
            0.0,
            0.0,
            0.0,
            0.0,
            0.0,
            0.0,
            0.0,
            0.0,
            0.0,
            0.0,
            0.0,
            0.0
        ],
        [
            0.0,
            0.0,
            0.0,
            0.0,
            0.0,
            0.0,
            0.0,
            0.0,
            0.0,
            0.0,
            0.0,
            0.0
        ],
        [
            0.0,
            0.0,
            0.0,
            0.0,
            0.0,
            0.0,
            0.0,
            0.0,
            0.0,
            0.0,
            0.0,
            0.0
        ]
    ],
    "prevVerb": [
        [
            0.0,
            0.0,
            0.0,
            0.0,
            0.0,
            0.0,
            0.0,
            0.0,
            0.0,
            0.0,
            0.0,
            0.0,
            0.0
        ],
        [
            0.0,
            0.0,
            0.0,
            0.0,
            0.0,
            0.0,
            0.0,
            0.0,
            0.0,
            0.0,
            0.0,
            0.0,
            0.0
        ],
        [
            0.0,
            0.0,
            0.0,
            0.0,
            0.0,
            0.0,
            0.0,
            0.0,
            0.0,
            0.0,
            0.0,
            0.007194244604316547,
            0.0
        ],
        [
            0.0,
            0.1870503597122303,
            0.007194244604316547,
            0.0,
            0.007194244604316547,
            0.02158273381294964,
            0.014388489208633094,
            0.0,
            0.0,
            0.0,
            0.0,
            0.007194244604316547,
            0.0
        ],
        [
            0.0,
            0.16546762589928055,
            0.0,
            0.0,
            0.007194244604316547,
            0.0,
            0.014388489208633094,
            0.0,
            0.0,
            0.0,
            0.0,
            0.0,
            0.0
        ],
        [
            0.0,
            0.07194244604316546,
            0.0,
            0.0,
            0.0,
            0.0,
            0.007194244604316547,
            0.0,
            0.0,
            0.0,
            0.0,
            0.0,
            0.0
        ],
        [
            0.0,
            0.0,
            0.0,
            0.0,
            0.0,
            0.0,
            0.0,
            0.0,
            0.0,
            0.0,
            0.0,
            0.0,
            0.0
        ],
        [
            0.0,
            0.16546762589928057,
            0.007194244604316547,
            0.0,
            0.007194244604316547,
            0.0,
            0.04316546762589928,
            0.0,
            0.0,
            0.0,
            0.007194244604316547,
            0.07194244604316546,
            0.0
        ],
        [
            0.0,
            0.06474820143884895,
            0.0,
            0.0,
            0.0,
            0.014388489208633094,
            0.02158273381294962,
            0.0,
            0.007194244604316547,
            0.0,
            0.0,
            0.03597122302158273,
            0.0
        ],
        [
            0.0,
            0.0,
            0.0,
            0.0,
            0.0,
            0.0,
            0.0,
            0.0,
            0.0,
            0.0,
            0.0,
            0.0,
            0.0
        ],
        [
            0.0,
            0.02877697841726619,
            0.007194244604316547,
            0.0,
            0.0,
            0.0,
            0.0,
            0.0,
            0.0,
            0.0,
            0.0,
            0.0,
            0.0
        ],
        [
            0.0,
            0.0,
            0.0,
            0.0,
            0.0,
            0.0,
            0.0,
            0.0,
            0.0,
            0.0,
            0.0,
            0.0,
            0.0
        ]
    ],
    "pronVerb": [
        [
            0.0,
            0.0,
            0.0,
            0.0,
            0.0,
            0.0
        ],
        [
            0.0,
            0.0,
            0.0,
            0.0,
            0.0,
            0.0
        ],
        [
            0.006578947368421052,
            0.006578947368421052,
            0.006578947368421052,
            0.006578947368421052,
            0.006578947368421052,
            0.006578947368421052
        ],
        [
            0.019736842105263153,
            0.0,
            0.118421052631579,
            0.0,
            0.0,
            0.09210526315789473
        ],
        [
            0.11842105263157894,
            0.0,
            0.006578947368421052,
            0.0,
            0.0,
            0.046052631578947366
        ],
        [
            0.0,
            0.0,
            0.05921052631578947,
            0.006578947368421052,
            0.0,
            0.013157894736842105
        ],
        [
            0.0,
            0.0,
            0.0,
            0.0,
            0.0,
            0.0
        ],
        [
            0.13157894736842118,
            0.0,
            0.09210526315789473,
            0.0,
            0.0,
            0.05921052631578947
        ],
        [
            0.019736842105263157,
            0.019736842105263153,
            0.09210526315789473,
            0.006578947368421052,
            0.006578947368421052,
            0.019736842105263153
        ],
        [
            0.0,
            0.0,
            0.0,
            0.0,
            0.0,
            0.0
        ],
        [
            0.019736842105263136,
            0.0,
            0.0,
            0.0,
            0.0,
            0.013157894736842105
        ],
        [
            0.0,
            0.0,
            0.0,
            0.0,
            0.0,
            0.0
        ],
        [
            0.0,
            0.0,
            0.0,
            0.0,
            0.0,
            0.0
        ]
    ],
    "workflow": {
        "functions": [
            [
                "isIntj",
                "isAux",
                "isNum",
                "isConj",
                "isPron",
                "isPunc",
                "isAdj",
                "isDet",
                "null",
                "isPrep",
                "isAdv",
                "setNuc",
                "isVerb",
                "isNoun"
            ]
        ],
        "graph": {
            "connects": [
                [
                    0.0,
                    0.48749999999999966,
                    0.05625,
                    0.0031249999999999993,
                    0.018749999999999992,
                    0.0,
                    0.0,
                    0.0,
                    0.003125,
                    0.0031249999999999993,
                    0.0,
                    0.0
                ],
                [
                    0.025,
                    0.07500000000000002,
                    0.02187499999999999,
                    0.10625,
                    0.28749999999999987,
                    0.025,
                    0.034375,
                    0.0,
                    0.028125,
                    0.0,
                    0.024999999999999994,
                    0.04375000000000001
                ],
                [
                    0.031250000000000014,
                    0.03124999999999999,
                    0.0,
                    0.006249999999999999,
                    0.015624999999999995,
                    0.0,
                    0.0031249999999999993,
                    0.0,
                    0.006249999999999999,
                    0.0,
                    0.0,
                    0.006249999999999999
                ],
                [
                    0.09687499999999999,
                    0.1375,
                    0.018749999999999992,
                    0.0,
                    0.015624999999999995,
                    0.009374999999999996,
                    0.006249999999999999,
                    0.0,
                    0.0,
                    0.0,
                    0.0,
                    0.0
                ],
                [
                    0.14687499999999998,
                    0.06874999999999999,
                    0.046874999999999986,
                    0.13125000000000003,
                    0.021875000000000006,
                    0.021875000000000006,
                    0.018750000000000003,
                    0.0,
                    0.015624999999999997,
                    0.0125,
                    0.0,
                    0.0
                ],
                [
                    0.0,
                    0.0,
                    0.003125,
                    0.006249999999999999,
                    0.015625000000000007,
                    0.031250000000000014,
                    0.0031249999999999993,
                    0.0,
                    0.0,
                    0.0,
                    0.0031249999999999993,
                    0.0031249999999999993
                ],
                [
                    0.0,
                    0.046874999999999986,
                    0.009374999999999998,
                    0.0,
                    0.03125,
                    0.0,
                    0.0,
                    0.0,
                    0.0,
                    0.0,
                    0.0,
                    0.006249999999999999
                ],
                [
                    0.0,
                    0.0,
                    0.0,
                    0.0,
                    0.0,
                    0.0,
                    0.0,
                    0.0,
                    0.0,
                    0.0,
                    0.0,
                    0.0
                ],
                [
                    0.009374999999999996,
                    0.028125,
                    0.0,
                    0.0,
                    0.015624999999999995,
                    0.0,
                    0.006249999999999999,
                    0.0,
                    0.0,
                    0.0,
                    0.0,
                    0.0
                ],
                [
                    0.0,
                    0.0125,
                    0.0,
                    0.0031249999999999993,
                    0.0,
                    0.0,
                    0.0,
                    0.0,
                    0.0,
                    0.0,
                    0.0,
                    0.0
                ],
                [
                    0.003125,
                    0.006249999999999999,
                    0.0,
                    0.0,
                    0.006249999999999999,
                    0.0,
                    0.0031249999999999993,
                    0.0,
                    0.0,
                    0.0,
                    0.0,
                    0.0
                ],
                [
                    0.0,
                    0.0,
                    0.0,
                    0.0,
                    0.059375,
                    0.0,
                    0.0,
                    0.0,
                    0.0,
                    0.0,
                    0.0,
                    0.0
                ]
            ],
            "factor": 320.0,
            "factorFinnish": 143.0,
            "factorStart": 143.0,
            "finnish": [
                [
                    0.0,
                    0.2587412587412587,
                    0.055944055944055944,
                    0.0,
                    0.006993006993006993,
                    0.0,
                    0.0,
                    0.0,
                    0.0,
                    0.0,
                    0.0,
                    0.0
                ],
                [
                    0.0,
                    0.1048951048951049,
                    0.027972027972027972,
                    0.0,
                    0.0,
                    0.02097902097902098,
                    0.0,
                    0.0,
                    0.0,
                    0.0,
                    0.013986013986013986,
                    0.0
                ],
                [
                    0.0,
                    0.03496503496503497,
                    0.0,
                    0.0,
                    0.0,
                    0.0,
                    0.0,
                    0.0,
                    0.0,
                    0.0,
                    0.0,
                    0.0
                ],
                [
                    0.0,
                    0.16783216783216784,
                    0.02097902097902098,
                    0.0,
                    0.013986013986013986,
                    0.013986013986013986,
                    0.0,
                    0.0,
                    0.0,
                    0.0,
                    0.0,
                    0.0
                ],
                [
                    0.0,
                    0.05594405594405593,
                    0.048951048951048945,
                    0.0,
                    0.013986013986013986,
                    0.006993006993006993,
                    0.013986013986013986,
                    0.0,
                    0.0,
                    0.0,
                    0.0,
                    0.0
                ],
                [
                    0.0,
                    0.0,
                    0.0,
                    0.0,
                    0.0,
                    0.027972027972027958,
                    0.0,
                    0.0,
                    0.0,
                    0.0,
                    0.006993006993006993,
                    0.0
                ],
                [
                    0.0,
                    0.048951048951048945,
                    0.0,
                    0.0,
                    0.0,
                    0.0,
                    0.0,
                    0.0,
                    0.0,
                    0.0,
                    0.0,
                    0.0
                ],
                [
                    0.0,
                    0.0,
                    0.0,
                    0.0,
                    0.0,
                    0.0,
                    0.0,
                    0.0,
                    0.0,
                    0.0,
                    0.0,
                    0.0
                ],
                [
                    0.0,
                    0.0,
                    0.0,
                    0.0,
                    0.006993006993006993,
                    0.0,
                    0.006993006993006993,
                    0.0,
                    0.0,
                    0.0,
                    0.0,
                    0.0
                ],
                [
                    0.0,
                    0.02097902097902098,
                    0.0,
                    0.0,
                    0.0,
                    0.0,
                    0.0,
                    0.0,
                    0.0,
                    0.0,
                    0.0,
                    0.0
                ],
                [
                    0.0,
                    0.0,
                    0.0,
                    0.0,
                    0.0,
                    0.0,
                    0.0,
                    0.0,
                    0.0,
                    0.0,
                    0.0,
                    0.0
                ],
                [
                    0.0,
                    0.0,
                    0.0,
                    0.0,
                    0.0,
                    0.0,
                    0.0,
                    0.0,
                    0.0,
                    0.0,
                    0.0,
                    0.0
                ]
            ],
            "first": 0,
            "height": 12,
            "id": "",
            "iterations": 143,
            "name": "workflow",
            "nodeNames": [
                "DET",
                "NOUN",
                "ADJ",
                "PREP",
                "VERB",
                "ADV",
                "PRON",
                "INTJ",
                "CONJ",
                "NUM",
                "PUNC",
                "AUX"
            ],
            "nodes": [
                0,
                1,
                2,
                3,
                4,
                5,
                6,
                7,
                8,
                9,
                10,
                11
            ],
            "start": [
                [
                    0.0,
                    0.5314685314685312,
                    0.027972027972027972,
                    0.0,
                    0.020979020979020976,
                    0.0,
                    0.0,
                    0.0,
                    0.0,
                    0.0,
                    0.0,
                    0.0
                ],
                [
                    0.0,
                    0.0,
                    0.0,
                    0.0,
                    0.11888111888111894,
                    0.006993006993006993,
                    0.006993006993006993,
                    0.0,
                    0.04195804195804196,
                    0.0,
                    0.013986013986013986,
                    0.006993006993006993
                ],
                [
                    0.0,
                    0.02097902097902098,
                    0.0,
                    0.0,
                    0.0,
                    0.0,
                    0.0,
                    0.0,
                    0.0,
                    0.0,
                    0.0,
                    0.006993006993006993
                ],
                [
                    0.04195804195804196,
                    0.006993006993006993,
                    0.0,
                    0.0,
                    0.0,
                    0.0,
                    0.013986013986013986,
                    0.0,
                    0.0,
                    0.0,
                    0.0,
                    0.0
                ],
                [
                    0.013986013986013986,
                    0.0,
                    0.0,
                    0.006993006993006993,
                    0.006993006993006993,
                    0.0,
                    0.0,
                    0.0,
                    0.006993006993006993,
                    0.0,
                    0.0,
                    0.0
                ],
                [
                    0.0,
                    0.0,
                    0.0,
                    0.006993006993006993,
                    0.006993006993006993,
                    0.006993006993006993,
                    0.0,
                    0.0,
                    0.0,
                    0.0,
                    0.0,
                    0.0
                ],
                [
                    0.0,
                    0.013986013986013986,
                    0.0,
                    0.0,
                    0.03496503496503494,
                    0.0,
                    0.0,
                    0.0,
                    0.0,
                    0.0,
                    0.0,
                    0.013986013986013986
                ],
                [
                    0.0,
                    0.0,
                    0.0,
                    0.0,
                    0.0,
                    0.0,
                    0.0,
                    0.0,
                    0.0,
                    0.0,
                    0.0,
                    0.0
                ],
                [
                    0.013986013986013986,
                    0.0,
                    0.0,
                    0.0,
                    0.0,
                    0.0,
                    0.0,
                    0.0,
                    0.0,
                    0.0,
                    0.0,
                    0.0
                ],
                [
                    0.0,
                    0.0,
                    0.0,
                    0.0,
                    0.0,
                    0.0,
                    0.0,
                    0.0,
                    0.0,
                    0.0,
                    0.0,
                    0.0
                ],
                [
                    0.0,
                    0.0,
                    0.0,
                    0.0,
                    0.0,
                    0.0,
                    0.0,
                    0.0,
                    0.0,
                    0.0,
                    0.0,
                    0.0
                ],
                [
                    0.0,
                    0.0,
                    0.0,
                    0.0,
                    0.0,
                    0.0,
                    0.0,
                    0.0,
                    0.0,
                    0.0,
                    0.0,
                    0.0
                ]
            ],
            "width": 12
        },
        "nodes": [
            {
                "function": "isDet",
                "id": 0,
                "name": "DET"
            },
            {
                "function": "isNoun",
                "id": 1,
                "name": "NOUN"
            },
            {
                "function": "isAdj",
                "id": 2,
                "name": "ADJ"
            },
            {
                "function": "isPrep",
                "id": 3,
                "name": "PREP"
            },
            {
                "function": "isVerb",
                "id": 4,
                "name": "VERB"
            },
            {
                "function": "isAdv",
                "id": 5,
                "name": "ADV"
            },
            {
                "function": "isPron",
                "id": 6,
                "name": "PRON"
            },
            {
                "function": "isIntj",
                "id": 7,
                "name": "INTJ"
            },
            {
                "function": "isConj",
                "id": 8,
                "name": "CONJ"
            },
            {
                "function": "isNum",
                "id": 9,
                "name": "NUM"
            },
            {
                "function": "isPunc",
                "id": 10,
                "name": "PUNC"
            },
            {
                "function": "isAux",
                "id": 11,
                "name": "AUX"
            }
        ]
    }
}